random_weighted_useragent/__init__.py
random_weighted_useragent-1.0.0.dist-info/LICENSE
random_weighted_useragent-1.0.0.dist-info/METADATA
random_weighted_useragent-1.0.0.dist-info/WHEEL
random_weighted_useragent-1.0.0.dist-info/top_level.txt
random_weighted_useragent-1.0.0.dist-info/RECORD
