Metadata-Version: 2.1
Name: random_weighted_useragent
Version: 1.0.0
Summary: Randomly returns a weighted user agent for firewall evasion
Author-email: Lilly Aronleigh <ghostoverflow256@gmail.com>
Project-URL: Homepage, https://github.com/GhostDog98/random-ua
Project-URL: Issues, https://github.com/GhostDog98/random-ua/issues
Classifier: Programming Language :: Python :: 3
Classifier: License :: OSI Approved :: GNU Affero General Public License v3 or later (AGPLv3+)
Classifier: Operating System :: OS Independent
Requires-Python: >=3.8
License-File: LICENSE
